SLMcontroller/AmplitudeMask.py
SLMcontroller/CameraFunctions.py
SLMcontroller/FlatnessCorrection.py
SLMcontroller/FourierWavefrontOptim.py
SLMcontroller/Grating.py
SLMcontroller/Lens.py
SLMcontroller/MainGUI.py
SLMcontroller/Meshing_process.py
SLMcontroller/OpticalElement.py
SLMcontroller/Phase_pattern.py
SLMcontroller/Remote_control.py
SLMcontroller/WavefrontOptim.py
SLMcontroller/Zernike.py
SLMcontroller/__init__.py
SLMcontroller/__main__.py
SLMcontroller/settings.py
SLMcontroller/utils.py
SLMcontroller-1.0.23.dist-info/LICENSE
SLMcontroller-1.0.23.dist-info/METADATA
SLMcontroller-1.0.23.dist-info/WHEEL
SLMcontroller-1.0.23.dist-info/entry_points.txt
SLMcontroller-1.0.23.dist-info/top_level.txt
SLMcontroller-1.0.23.dist-info/RECORD
