Metadata-Version: 2.1
Name: SLMcontroller
Version: 1.0.23
Summary: An app for controlling SLMs
Author-email: "M. Mazzanti" <githubpagescontactme@gmail.com>
Maintainer-email: "M. Mazzanti" <githubpagescontactme@gmail.com>
License: GNU GENERAL PUBLIC LICENSE
Project-URL: Homepage, https://github.com/mmazzanti/SLMcontroller
Project-URL: Bug Reports, https://github.com/mmazzanti/SLMcontroller/issues
Project-URL: Funding, https://www.buymeacoffee.com/mmazzanti
Project-URL: Source, https://github.com/mmazzanti/SLMcontroller
Keywords: SLM,Optical tweezers,Holography,Spatial light modulator
Classifier: Development Status :: 3 - Alpha
Classifier: Intended Audience :: Developers
Classifier: Topic :: Scientific/Engineering :: Physics
Classifier: Topic :: Scientific/Engineering
Classifier: Topic :: System :: Hardware
Classifier: Topic :: Utilities
Classifier: License :: OSI Approved :: GNU General Public License v3 or later (GPLv3+)
Classifier: Programming Language :: Python :: 3
Classifier: Programming Language :: Python :: 3.7
Classifier: Programming Language :: Python :: 3.8
Classifier: Programming Language :: Python :: 3.9
Classifier: Programming Language :: Python :: 3.10
Classifier: Programming Language :: Python :: 3.11
Classifier: Programming Language :: Python :: 3 :: Only
Requires-Python: >=3.7
License-File: LICENSE
Requires-Dist: flask>=3
Requires-Dist: gmsh>=4
Requires-Dist: PyQt6
Requires-Dist: Pillow
Requires-Dist: opencv-python
Requires-Dist: numpy
Requires-Dist: numba
